{
 "lastUpdated": "2026-07-15 15:46:04",
 "totals": {
  "customers": 688602,
  "outages": 156,
  "incidents": 11
 },
 "southport": null,
 "lincolnCounty": {
  "level": "county",
  "opco": "CMP",
  "county": "LINCOLN",
  "customers": 28935,
  "Outages": 7,
  "incidents": 2,
  "EstRest": "7/15/2026 6:00:00 PM"
 },
 "towns": [
  {
   "level": "town",
   "opco": "CMP",
   "county": "PENOBSCOT",
   "town": "HERMON",
   "customers": 3092,
   "Outages": 4,
   "incidents": 1,
   "EstRest": "7/15/2026 5:45:00 PM"
  },
  {
   "level": "town",
   "opco": "CMP",
   "county": "PENOBSCOT",
   "town": "GLENBURN",
   "customers": 213,
   "Outages": 14,
   "incidents": 1,
   "EstRest": "7/15/2026 5:45:00 PM"
  },
  {
   "level": "town",
   "opco": "CMP",
   "county": "CUMBERLAND",
   "town": "FALMOUTH",
   "customers": 6547,
   "Outages": 42,
   "incidents": 1,
   "EstRest": "7/15/2026 5:30:00 PM"
  },
  {
   "level": "town",
   "opco": "CMP",
   "county": "CUMBERLAND",
   "town": "CASCO",
   "customers": 3231,
   "Outages": 1,
   "incidents": 1,
   "EstRest": "7/15/2026 5:45:00 PM"
  },
  {
   "level": "town",
   "opco": "CMP",
   "county": "SAGADAHOC",
   "town": "TOPSHAM",
   "customers": 5447,
   "Outages": 7,
   "incidents": 2,
   "EstRest": "7/15/2026 5:45:00 PM"
  },
  {
   "level": "town",
   "opco": "CMP",
   "county": "OXFORD",
   "town": "LOVELL",
   "customers": 1413,
   "Outages": 21,
   "incidents": 1,
   "EstRest": "7/15/2026 5:45:00 PM"
  },
  {
   "level": "town",
   "opco": "CMP",
   "county": "WALDO",
   "town": "MORRILL",
   "customers": 502,
   "Outages": 1,
   "incidents": 1,
   "EstRest": "7/15/2026 4:45:00 PM"
  },
  {
   "level": "town",
   "opco": "CMP",
   "county": "YORK",
   "town": "SANFORD",
   "customers": 11628,
   "Outages": 50,
   "incidents": 1,
   "EstRest": "7/15/2026 4:15:00 PM"
  },
  {
   "level": "town",
   "opco": "CMP",
   "county": "YORK",
   "town": "NORTH BERWICK",
   "customers": 2615,
   "Outages": 8,
   "incidents": 1,
   "EstRest": "7/15/2026 4:15:00 PM"
  },
  {
   "level": "town",
   "opco": "CMP",
   "county": "YORK",
   "town": "LIMINGTON",
   "customers": 2143,
   "Outages": 1,
   "incidents": 1,
   "EstRest": "7/15/2026 5:15:00 PM"
  },
  {
   "level": "town",
   "opco": "CMP",
   "county": "LINCOLN",
   "town": "SOMERVILLE PLT",
   "customers": 380,
   "Outages": 1,
   "incidents": 1,
   "EstRest": "7/15/2026 5:45:00 PM"
  },
  {
   "level": "town",
   "opco": "CMP",
   "county": "LINCOLN",
   "town": "DRESDEN",
   "customers": 1039,
   "Outages": 6,
   "incidents": 1,
   "EstRest": "7/15/2026 6:00:00 PM"
  },
  {
   "level": "street",
   "opco": "CMP",
   "county": "PENOBSCOT",
   "town": "HERMON",
   "hamlet": "HERMON",
   "street": "KELLEY RD",
   "customers": 4,
   "Outages": 3,
   "incidents": 1,
   "EstRest": "7/15/2026 5:45:00 PM",
   "crewstatus": "     ",
   "cause": "",
   "incidentnumber": "003L1V"
  },
  {
   "level": "street",
   "opco": "CMP",
   "county": "PENOBSCOT",
   "town": "GLENBURN",
   "hamlet": "GLENBURN",
   "street": "KELLEY RD",
   "customers": 23,
   "Outages": 13,
   "incidents": 1,
   "EstRest": "7/15/2026 5:45:00 PM",
   "crewstatus": "     ",
   "cause": "",
   "incidentnumber": "003L1V"
  },
  {
   "level": "street",
   "opco": "CMP",
   "county": "CUMBERLAND",
   "town": "FALMOUTH",
   "hamlet": "FALMOUTH",
   "street": "IVY PL",
   "customers": 2,
   "Outages": 2,
   "incidents": 1,
   "EstRest": "7/15/2026 5:30:00 PM",
   "crewstatus": "ENRT ",
   "cause": "",
   "incidentnumber": "003L1O"
  },
  {
   "level": "street",
   "opco": "CMP",
   "county": "CUMBERLAND",
   "town": "CASCO",
   "hamlet": "CASCO",
   "street": "LEANDER LN",
   "customers": 6,
   "Outages": 1,
   "incidents": 1,
   "EstRest": "7/15/2026 5:45:00 PM",
   "crewstatus": "DISP ",
   "cause": "",
   "incidentnumber": "003L21"
  },
  {
   "level": "street",
   "opco": "CMP",
   "county": "OXFORD",
   "town": "LOVELL",
   "hamlet": "LOVELL",
   "street": "RUDY VALLEE LN",
   "customers": 6,
   "Outages": 3,
   "incidents": 1,
   "EstRest": "7/15/2026 5:45:00 PM",
   "crewstatus": "DISP ",
   "cause": "",
   "incidentnumber": "003L22"
  },
  {
   "level": "street",
   "opco": "CMP",
   "county": "WALDO",
   "town": "MORRILL",
   "hamlet": "MORRILL",
   "street": "WEYMOUTH RD",
   "customers": 60,
   "Outages": 1,
   "incidents": 1,
   "EstRest": "7/15/2026 4:45:00 PM",
   "crewstatus": "ENRT ",
   "cause": "",
   "incidentnumber": "003L10"
  },
  {
   "level": "street",
   "opco": "CMP",
   "county": "YORK",
   "town": "SANFORD",
   "hamlet": "SANFORD",
   "street": "WALNUT BROOK RD",
   "customers": 8,
   "Outages": 8,
   "incidents": 1,
   "EstRest": "7/15/2026 4:15:00 PM",
   "crewstatus": "ONST ",
   "cause": "",
   "incidentnumber": "003L0V"
  },
  {
   "level": "street",
   "opco": "CMP",
   "county": "YORK",
   "town": "NORTH BERWICK",
   "hamlet": "NORTH BERWICK",
   "street": "TWOMBLEY RD",
   "customers": 1,
   "Outages": 1,
   "incidents": 1,
   "EstRest": "7/15/2026 4:15:00 PM",
   "crewstatus": "ONST ",
   "cause": "",
   "incidentnumber": "003L0V"
  },
  {
   "level": "street",
   "opco": "CMP",
   "county": "YORK",
   "town": "LIMINGTON",
   "hamlet": "LIMINGTON",
   "street": "OSSIPEE TRL",
   "customers": 126,
   "Outages": 1,
   "incidents": 1,
   "EstRest": "7/15/2026 5:15:00 PM",
   "crewstatus": "     ",
   "cause": "",
   "incidentnumber": "003L1K"
  },
  {
   "level": "street",
   "opco": "CMP",
   "county": "LINCOLN",
   "town": "SOMERVILLE PLT",
   "hamlet": "SOMERVILLE PLT",
   "street": "ROCKLAND RD",
   "customers": 28,
   "Outages": 1,
   "incidents": 1,
   "EstRest": "7/15/2026 5:45:00 PM",
   "crewstatus": "ENRT ",
   "cause": "",
   "incidentnumber": "003L1R"
  },
  {
   "level": "street",
   "opco": "CMP",
   "county": "LINCOLN",
   "town": "DRESDEN",
   "hamlet": "DRESDEN",
   "street": "RUSSELL LN",
   "customers": 8,
   "Outages": 6,
   "incidents": 1,
   "EstRest": "7/15/2026 6:00:00 PM",
   "crewstatus": "     ",
   "cause": "",
   "incidentnumber": "003L20"
  }
 ]
}